fixations/__init__.py
fixations/fix_explore.py
fixations/fix_parse_log.py
fixations/fix_repository_2010_edition_20200402/.DS_Store
fixations/fix_repository_2010_edition_20200402/FIX.4.0/Base/Components.xml
fixations/fix_repository_2010_edition_20200402/FIX.4.0/Base/Datatypes.xml
fixations/fix_repository_2010_edition_20200402/FIX.4.0/Base/Enums.xml
fixations/fix_repository_2010_edition_20200402/FIX.4.0/Base/Fields.xml
fixations/fix_repository_2010_edition_20200402/FIX.4.0/Base/Messages.xml
fixations/fix_repository_2010_edition_20200402/FIX.4.0/Base/MsgContents.xml
fixations/fix_repository_2010_edition_20200402/FIX.4.1/Base/Components.xml
fixations/fix_repository_2010_edition_20200402/FIX.4.1/Base/Datatypes.xml
fixations/fix_repository_2010_edition_20200402/FIX.4.1/Base/Enums.xml
fixations/fix_repository_2010_edition_20200402/FIX.4.1/Base/Fields.xml
fixations/fix_repository_2010_edition_20200402/FIX.4.1/Base/Messages.xml
fixations/fix_repository_2010_edition_20200402/FIX.4.1/Base/MsgContents.xml
fixations/fix_repository_2010_edition_20200402/FIX.4.2/.DS_Store
fixations/fix_repository_2010_edition_20200402/FIX.4.2/Base/Components.xml
fixations/fix_repository_2010_edition_20200402/FIX.4.2/Base/Datatypes.xml
fixations/fix_repository_2010_edition_20200402/FIX.4.2/Base/Enums.xml
fixations/fix_repository_2010_edition_20200402/FIX.4.2/Base/Fields.xml
fixations/fix_repository_2010_edition_20200402/FIX.4.2/Base/Messages.xml
fixations/fix_repository_2010_edition_20200402/FIX.4.2/Base/MsgContents.xml
fixations/fix_repository_2010_edition_20200402/FIX.4.3/Base/Components.xml
fixations/fix_repository_2010_edition_20200402/FIX.4.3/Base/Datatypes.xml
fixations/fix_repository_2010_edition_20200402/FIX.4.3/Base/Enums.xml
fixations/fix_repository_2010_edition_20200402/FIX.4.3/Base/Fields.xml
fixations/fix_repository_2010_edition_20200402/FIX.4.3/Base/Messages.xml
fixations/fix_repository_2010_edition_20200402/FIX.4.3/Base/MsgContents.xml
fixations-0.2.41.dist-info/METADATA
fixations-0.2.41.dist-info/WHEEL
fixations-0.2.41.dist-info/entry_points.txt
fixations-0.2.41.dist-info/RECORD
