Metadata-Version: 2.1
Name: fixations
Version: 0.2.41
Summary: This is a set of tools to look up / visualize FIX protocol data.
Home-page: https://github.com/jeromegit/fixations
License: GPL-3.0-or-later
Keywords: fix,fix-protocol
Author: Jerome Provensal
Author-email: jeromegit@provensal.com
Requires-Python: >=3.7
Classifier: License :: OSI Approved :: GNU General Public License v3 or later (GPLv3+)
Classifier: Programming Language :: Python :: 3
Classifier: Programming Language :: Python :: 3.7
Classifier: Programming Language :: Python :: 3.8
Classifier: Programming Language :: Python :: 3.9
Classifier: Programming Language :: Python :: 3.10
Classifier: Programming Language :: Python :: 3.11
Requires-Dist: dataclasses-json (>=0.5.7,<0.6.0)
Requires-Dist: flask (>=2.2.2,<3.0.0)
Requires-Dist: gunicorn (>=20.1.0,<21.0.0)
Requires-Dist: requests (>=2.31.0,<3.0.0)
Requires-Dist: tabulate (>=0.9.0,<0.10.0)
Requires-Dist: termcolor (>=2.1.1,<3.0.0)
Requires-Dist: urwid (>=2.1.2,<3.0.0)
